pflib/__init__.py
pflib/pflib.py
pflib-0.0.3.dist-info/METADATA
pflib-0.0.3.dist-info/WHEEL
pflib-0.0.3.dist-info/top_level.txt
pflib-0.0.3.dist-info/RECORD
