Metadata-Version: 2.1
Name: pflib
Version: 0.0.3
Summary: Simple library for send metric into pushgateway
Home-page: https://github.com/OldTyT/pflib
Author: OldTyT
Requires-Dist: urllib3
